{
  "mirroredOrders": {
    "260413150286981": {
      "sourceOrderId": "260413150286981",
      "followers": {
        "follower_1": {
          "sourceOrderId": "260413150286981",
          "sourceStatus": "COMPLETE",
          "mirrorStatus": "dry_run",
          "followerPreview": {
            "variety": "regular",
            "exchange": "NFO",
            "tradingsymbol": "NIFTY2641323650CE",
            "transaction_type": "SELL",
            "order_type": "LIMIT",
            "quantity": 65,
            "product": "NRML",
            "validity": "DAY",
            "disclosed_quantity": 0,
            "price": 52.35,
            "trigger_price": 0,
            "tag": "CPY50286981"
          },
          "followerId": "follower_1",
          "updatedAt": "2026-04-13T03:59:08.068Z"
        },
        "follower_2": {
          "sourceOrderId": "260413150286981",
          "sourceStatus": "COMPLETE",
          "mirrorStatus": "dry_run",
          "followerPreview": {
            "variety": "regular",
            "exchange": "NFO",
            "tradingsymbol": "NIFTY2641323650CE",
            "transaction_type": "SELL",
            "order_type": "LIMIT",
            "quantity": 65,
            "product": "NRML",
            "validity": "DAY",
            "disclosed_quantity": 0,
            "price": 52.35,
            "trigger_price": 0,
            "tag": "CPY50286981"
          },
          "followerId": "follower_2",
          "updatedAt": "2026-04-13T03:59:08.070Z"
        }
      },
      "updatedAt": "2026-04-13T03:59:08.070Z"
    },
    "260413150295943": {
      "sourceOrderId": "260413150295943",
      "followers": {
        "follower_1": {
          "sourceOrderId": "260413150295943",
          "sourceStatus": "COMPLETE",
          "mirrorStatus": "dry_run",
          "followerPreview": {
            "variety": "regular",
            "exchange": "NFO",
            "tradingsymbol": "NIFTY2641323650CE",
            "transaction_type": "BUY",
            "order_type": "LIMIT",
            "quantity": 65,
            "product": "NRML",
            "validity": "DAY",
            "disclosed_quantity": 0,
            "price": 54.6,
            "trigger_price": 0,
            "tag": "CPY50295943"
          },
          "followerId": "follower_1",
          "updatedAt": "2026-04-13T04:00:05.462Z"
        },
        "follower_2": {
          "sourceOrderId": "260413150295943",
          "sourceStatus": "COMPLETE",
          "mirrorStatus": "dry_run",
          "followerPreview": {
            "variety": "regular",
            "exchange": "NFO",
            "tradingsymbol": "NIFTY2641323650CE",
            "transaction_type": "BUY",
            "order_type": "LIMIT",
            "quantity": 65,
            "product": "NRML",
            "validity": "DAY",
            "disclosed_quantity": 0,
            "price": 54.6,
            "trigger_price": 0,
            "tag": "CPY50295943"
          },
          "followerId": "follower_2",
          "updatedAt": "2026-04-13T04:00:05.463Z"
        }
      },
      "updatedAt": "2026-04-13T04:00:05.463Z"
    },
    "260413150319818": {
      "sourceOrderId": "260413150319818",
      "followers": {
        "follower_1": {
          "sourceOrderId": "260413150319818",
          "sourceStatus": "COMPLETE",
          "mirrorStatus": "placed",
          "followerOrderId": "260413170280303",
          "followerVariety": "regular",
          "followerId": "follower_1",
          "updatedAt": "2026-04-13T04:01:49.347Z"
        }
      },
      "updatedAt": "2026-04-13T04:01:49.347Z"
    },
    "260413150352125": {
      "sourceOrderId": "260413150352125",
      "followers": {
        "follower_1": {
          "sourceOrderId": "260413150352125",
          "sourceStatus": "COMPLETE",
          "mirrorStatus": "placed",
          "followerOrderId": "260413170309467",
          "followerVariety": "regular",
          "followerId": "follower_1",
          "updatedAt": "2026-04-13T04:05:24.672Z"
        }
      },
      "updatedAt": "2026-04-13T04:05:24.672Z"
    },
    "260413150371504": {
      "sourceOrderId": "260413150371504",
      "followers": {
        "follower_1": {
          "sourceOrderId": "260413150371504",
          "sourceStatus": "COMPLETE",
          "mirrorStatus": "placed",
          "followerOrderId": "260413170327162",
          "followerVariety": "regular",
          "followerId": "follower_1",
          "updatedAt": "2026-04-13T04:07:23.837Z"
        }
      },
      "updatedAt": "2026-04-13T04:07:23.837Z"
    },
    "260413150372929": {
      "sourceOrderId": "260413150372929",
      "followers": {
        "follower_1": {
          "sourceOrderId": "260413150372929",
          "sourceStatus": "COMPLETE",
          "mirrorStatus": "placed",
          "followerOrderId": "260413170328317",
          "followerVariety": "regular",
          "followerId": "follower_1",
          "updatedAt": "2026-04-13T04:07:33.129Z"
        }
      },
      "updatedAt": "2026-04-13T04:07:33.129Z"
    },
    "260413150582015": {
      "sourceOrderId": "260413150582015",
      "followers": {
        "follower_2": {
          "sourceOrderId": "260413150582015",
          "sourceStatus": "COMPLETE",
          "mirrorStatus": "error",
          "errors": {
            "name": "KiteApiError",
            "message": "IP (20.197.12.34) is not allowed to place orders for this app. Update allowed IPs on the Kite developer console (https://developers.kite.trade).",
            "status": 403,
            "errorType": "PermissionException",
            "body": {
              "status": "error",
              "message": "IP (20.197.12.34) is not allowed to place orders for this app. Update allowed IPs on the Kite developer console (https://developers.kite.trade).",
              "data": null,
              "error_type": "PermissionException"
            }
          },
          "followerId": "follower_2",
          "updatedAt": "2026-04-13T04:37:17.878Z"
        },
        "follower_1": {
          "sourceOrderId": "260413150582015",
          "sourceStatus": "COMPLETE",
          "mirrorStatus": "placed",
          "followerOrderId": "260413170524575",
          "followerVariety": "regular",
          "followerId": "follower_1",
          "updatedAt": "2026-04-13T04:37:17.895Z"
        }
      },
      "updatedAt": "2026-04-13T04:37:17.895Z"
    },
    "260413150587467": {
      "sourceOrderId": "260413150587467",
      "followers": {
        "follower_2": {
          "sourceOrderId": "260413150587467",
          "sourceStatus": "COMPLETE",
          "mirrorStatus": "error",
          "errors": {
            "name": "KiteApiError",
            "message": "IP (20.197.12.34) is not allowed to place orders for this app. Update allowed IPs on the Kite developer console (https://developers.kite.trade).",
            "status": 403,
            "errorType": "PermissionException",
            "body": {
              "status": "error",
              "message": "IP (20.197.12.34) is not allowed to place orders for this app. Update allowed IPs on the Kite developer console (https://developers.kite.trade).",
              "data": null,
              "error_type": "PermissionException"
            }
          },
          "followerId": "follower_2",
          "updatedAt": "2026-04-13T04:38:22.197Z"
        },
        "follower_1": {
          "sourceOrderId": "260413150587467",
          "sourceStatus": "COMPLETE",
          "mirrorStatus": "placed",
          "followerOrderId": "260413170529869",
          "followerVariety": "regular",
          "followerId": "follower_1",
          "updatedAt": "2026-04-13T04:38:22.221Z"
        }
      },
      "updatedAt": "2026-04-13T04:38:22.221Z"
    },
    "260413150778698": {
      "sourceOrderId": "260413150778698",
      "followers": {
        "follower_2": {
          "sourceOrderId": "260413150778698",
          "sourceStatus": "COMPLETE",
          "mirrorStatus": "error",
          "errors": {
            "name": "KiteApiError",
            "message": "IP (20.197.12.34) is not allowed to place orders for this app. Update allowed IPs on the Kite developer console (https://developers.kite.trade).",
            "status": 403,
            "errorType": "PermissionException",
            "body": {
              "status": "error",
              "message": "IP (20.197.12.34) is not allowed to place orders for this app. Update allowed IPs on the Kite developer console (https://developers.kite.trade).",
              "data": null,
              "error_type": "PermissionException"
            }
          },
          "followerId": "follower_2",
          "updatedAt": "2026-04-13T05:13:24.902Z"
        },
        "follower_1": {
          "sourceOrderId": "260413150778698",
          "sourceStatus": "COMPLETE",
          "mirrorStatus": "placed",
          "followerOrderId": "260413170715560",
          "followerVariety": "regular",
          "followerId": "follower_1",
          "updatedAt": "2026-04-13T05:13:24.927Z"
        }
      },
      "updatedAt": "2026-04-13T05:13:24.927Z"
    },
    "260413150882181": {
      "sourceOrderId": "260413150882181",
      "followers": {
        "follower_2": {
          "sourceOrderId": "260413150882181",
          "sourceStatus": "OPEN",
          "mirrorStatus": "error",
          "errors": {
            "name": "KiteApiError",
            "message": "IP (20.197.12.34) is not allowed to place orders for this app. Update allowed IPs on the Kite developer console (https://developers.kite.trade).",
            "status": 403,
            "errorType": "PermissionException",
            "body": {
              "status": "error",
              "message": "IP (20.197.12.34) is not allowed to place orders for this app. Update allowed IPs on the Kite developer console (https://developers.kite.trade).",
              "data": null,
              "error_type": "PermissionException"
            }
          },
          "followerId": "follower_2",
          "updatedAt": "2026-04-13T05:38:18.349Z"
        },
        "follower_1": {
          "sourceOrderId": "260413150882181",
          "sourceStatus": "OPEN",
          "mirrorStatus": "cancelled",
          "followerOrderId": "260413170817947",
          "followerVariety": "regular",
          "followerId": "follower_1",
          "updatedAt": "2026-04-13T05:42:14.969Z"
        }
      },
      "updatedAt": "2026-04-13T05:42:14.969Z"
    },
    "260413150906727": {
      "sourceOrderId": "260413150906727",
      "followers": {
        "follower_2": {
          "sourceOrderId": "260413150906727",
          "sourceStatus": "OPEN",
          "mirrorStatus": "error",
          "errors": {
            "name": "KiteApiError",
            "message": "IP (20.197.12.34) is not allowed to place orders for this app. Update allowed IPs on the Kite developer console (https://developers.kite.trade).",
            "status": 403,
            "errorType": "PermissionException",
            "body": {
              "status": "error",
              "message": "IP (20.197.12.34) is not allowed to place orders for this app. Update allowed IPs on the Kite developer console (https://developers.kite.trade).",
              "data": null,
              "error_type": "PermissionException"
            }
          },
          "followerId": "follower_2",
          "updatedAt": "2026-04-13T05:45:33.125Z"
        },
        "follower_1": {
          "sourceOrderId": "260413150906727",
          "sourceStatus": "OPEN",
          "mirrorStatus": "placed",
          "followerOrderId": "260413170842486",
          "followerVariety": "regular",
          "followerId": "follower_1",
          "updatedAt": "2026-04-13T05:45:33.150Z"
        }
      },
      "updatedAt": "2026-04-13T05:45:33.150Z"
    }
  },
  "recentEvents": [
    {
      "at": "2026-04-13T05:45:33.151Z",
      "type": "mirror.error",
      "summary": "Failed to process source order",
      "detail": {
        "orderId": "260413150906727",
        "followerId": "follower_2",
        "message": "IP (20.197.12.34) is not allowed to place orders for this app. Update allowed IPs on the Kite developer console (https://developers.kite.trade)."
      }
    },
    {
      "at": "2026-04-13T05:45:33.151Z",
      "type": "mirror.placed",
      "summary": "Follower order placed",
      "detail": {
        "sourceOrderId": "260413150906727",
        "followerId": "follower_1",
        "followerOrderId": "260413170842486",
        "attempt": 1
      }
    },
    {
      "at": "2026-04-13T05:42:14.969Z",
      "type": "cancel.live",
      "summary": "Follower cancellation sent",
      "detail": {
        "sourceOrderId": "260413150882181",
        "followerId": "follower_1",
        "followerOrderId": "260413170817947"
      }
    },
    {
      "at": "2026-04-13T05:42:14.968Z",
      "type": "cancel.live",
      "summary": "Follower cancellation sent",
      "detail": {
        "sourceOrderId": "260413150882181",
        "followerId": "follower_1",
        "followerOrderId": "260413170817947"
      }
    },
    {
      "at": "2026-04-13T05:38:18.384Z",
      "type": "mirror.error",
      "summary": "Failed to process source order",
      "detail": {
        "orderId": "260413150882181",
        "followerId": "follower_2",
        "message": "IP (20.197.12.34) is not allowed to place orders for this app. Update allowed IPs on the Kite developer console (https://developers.kite.trade)."
      }
    },
    {
      "at": "2026-04-13T05:38:18.383Z",
      "type": "mirror.placed",
      "summary": "Follower order placed",
      "detail": {
        "sourceOrderId": "260413150882181",
        "followerId": "follower_1",
        "followerOrderId": "260413170817947",
        "attempt": 1
      }
    },
    {
      "at": "2026-04-13T05:13:24.928Z",
      "type": "mirror.error",
      "summary": "Failed to process source order",
      "detail": {
        "orderId": "260413150778698",
        "followerId": "follower_2",
        "message": "IP (20.197.12.34) is not allowed to place orders for this app. Update allowed IPs on the Kite developer console (https://developers.kite.trade)."
      }
    },
    {
      "at": "2026-04-13T05:13:24.927Z",
      "type": "mirror.placed",
      "summary": "Follower order placed",
      "detail": {
        "sourceOrderId": "260413150778698",
        "followerId": "follower_1",
        "followerOrderId": "260413170715560",
        "attempt": 1
      }
    },
    {
      "at": "2026-04-13T05:13:24.670Z",
      "type": "mirror.waiting",
      "summary": "Source order not actionable yet",
      "detail": {
        "orderId": "260413150778698",
        "status": "OPEN"
      }
    },
    {
      "at": "2026-04-13T04:38:22.223Z",
      "type": "mirror.error",
      "summary": "Failed to process source order",
      "detail": {
        "orderId": "260413150587467",
        "followerId": "follower_2",
        "message": "IP (20.197.12.34) is not allowed to place orders for this app. Update allowed IPs on the Kite developer console (https://developers.kite.trade)."
      }
    },
    {
      "at": "2026-04-13T04:38:22.222Z",
      "type": "mirror.placed",
      "summary": "Follower order placed",
      "detail": {
        "sourceOrderId": "260413150587467",
        "followerId": "follower_1",
        "followerOrderId": "260413170529869",
        "attempt": 1
      }
    },
    {
      "at": "2026-04-13T04:38:22.165Z",
      "type": "mirror.waiting",
      "summary": "Source order not actionable yet",
      "detail": {
        "orderId": "260413150587467",
        "status": "OPEN"
      }
    },
    {
      "at": "2026-04-13T04:37:17.896Z",
      "type": "mirror.error",
      "summary": "Failed to process source order",
      "detail": {
        "orderId": "260413150582015",
        "followerId": "follower_2",
        "message": "IP (20.197.12.34) is not allowed to place orders for this app. Update allowed IPs on the Kite developer console (https://developers.kite.trade)."
      }
    },
    {
      "at": "2026-04-13T04:37:17.895Z",
      "type": "mirror.placed",
      "summary": "Follower order placed",
      "detail": {
        "sourceOrderId": "260413150582015",
        "followerId": "follower_1",
        "followerOrderId": "260413170524575",
        "attempt": 1
      }
    },
    {
      "at": "2026-04-13T04:37:17.840Z",
      "type": "mirror.waiting",
      "summary": "Source order not actionable yet",
      "detail": {
        "orderId": "260413150582015",
        "status": "OPEN"
      }
    },
    {
      "at": "2026-04-13T04:34:53.836Z",
      "type": "auth.success",
      "summary": "follower_2 account authenticated",
      "detail": {
        "account": "follower_2",
        "userId": "AUY168"
      }
    },
    {
      "at": "2026-04-13T04:07:33.130Z",
      "type": "mirror.error",
      "summary": "Failed to process source order",
      "detail": {
        "orderId": "260413150372929",
        "followerId": "follower_2",
        "message": "Authenticate the follower_2 account first."
      }
    },
    {
      "at": "2026-04-13T04:07:33.130Z",
      "type": "mirror.placed",
      "summary": "Follower order placed",
      "detail": {
        "sourceOrderId": "260413150372929",
        "followerId": "follower_1",
        "followerOrderId": "260413170328317",
        "attempt": 1
      }
    },
    {
      "at": "2026-04-13T04:07:33.064Z",
      "type": "mirror.waiting",
      "summary": "Source order not actionable yet",
      "detail": {
        "orderId": "260413150372929",
        "status": "UPDATE"
      }
    },
    {
      "at": "2026-04-13T04:07:33.063Z",
      "type": "mirror.waiting",
      "summary": "Source order not actionable yet",
      "detail": {
        "orderId": "260413150372929",
        "status": "UPDATE"
      }
    },
    {
      "at": "2026-04-13T04:07:33.062Z",
      "type": "mirror.waiting",
      "summary": "Source order not actionable yet",
      "detail": {
        "orderId": "260413150372929",
        "status": "UPDATE"
      }
    },
    {
      "at": "2026-04-13T04:07:33.061Z",
      "type": "mirror.waiting",
      "summary": "Source order not actionable yet",
      "detail": {
        "orderId": "260413150372929",
        "status": "UPDATE"
      }
    },
    {
      "at": "2026-04-13T04:07:33.060Z",
      "type": "mirror.waiting",
      "summary": "Source order not actionable yet",
      "detail": {
        "orderId": "260413150372929",
        "status": "OPEN"
      }
    },
    {
      "at": "2026-04-13T04:07:23.838Z",
      "type": "mirror.error",
      "summary": "Failed to process source order",
      "detail": {
        "orderId": "260413150371504",
        "followerId": "follower_2",
        "message": "Authenticate the follower_2 account first."
      }
    },
    {
      "at": "2026-04-13T04:07:23.837Z",
      "type": "mirror.placed",
      "summary": "Follower order placed",
      "detail": {
        "sourceOrderId": "260413150371504",
        "followerId": "follower_1",
        "followerOrderId": "260413170327162",
        "attempt": 1
      }
    },
    {
      "at": "2026-04-13T04:07:23.778Z",
      "type": "mirror.ignored",
      "summary": "Skipped duplicate source order while in-flight",
      "detail": {
        "orderId": "260413150371504",
        "status": "UPDATE"
      }
    },
    {
      "at": "2026-04-13T04:07:23.775Z",
      "type": "mirror.waiting",
      "summary": "Source order not actionable yet",
      "detail": {
        "orderId": "260413150371504",
        "status": "UPDATE"
      }
    },
    {
      "at": "2026-04-13T04:07:23.774Z",
      "type": "mirror.waiting",
      "summary": "Source order not actionable yet",
      "detail": {
        "orderId": "260413150371504",
        "status": "OPEN"
      }
    },
    {
      "at": "2026-04-13T04:05:24.673Z",
      "type": "mirror.error",
      "summary": "Failed to process source order",
      "detail": {
        "orderId": "260413150352125",
        "followerId": "follower_2",
        "message": "Authenticate the follower_2 account first."
      }
    },
    {
      "at": "2026-04-13T04:05:24.672Z",
      "type": "mirror.placed",
      "summary": "Follower order placed",
      "detail": {
        "sourceOrderId": "260413150352125",
        "followerId": "follower_1",
        "followerOrderId": "260413170309467",
        "attempt": 1
      }
    },
    {
      "at": "2026-04-13T04:05:24.604Z",
      "type": "mirror.waiting",
      "summary": "Source order not actionable yet",
      "detail": {
        "orderId": "260413150352125",
        "status": "OPEN"
      }
    },
    {
      "at": "2026-04-13T04:01:49.349Z",
      "type": "mirror.error",
      "summary": "Failed to process source order",
      "detail": {
        "orderId": "260413150319818",
        "followerId": "follower_2",
        "message": "Authenticate the follower_2 account first."
      }
    },
    {
      "at": "2026-04-13T04:01:49.348Z",
      "type": "mirror.placed",
      "summary": "Follower order placed",
      "detail": {
        "sourceOrderId": "260413150319818",
        "followerId": "follower_1",
        "followerOrderId": "260413170280303",
        "attempt": 1
      }
    },
    {
      "at": "2026-04-13T04:01:48.622Z",
      "type": "mirror.waiting",
      "summary": "Source order not actionable yet",
      "detail": {
        "orderId": "260413150319818",
        "status": "OPEN"
      }
    },
    {
      "at": "2026-04-13T04:00:27.101Z",
      "type": "stream.connected",
      "summary": "Leader order stream connected",
      "detail": {
        "userId": "FEK088"
      }
    },
    {
      "at": "2026-04-13T04:00:27.014Z",
      "type": "stream.connecting",
      "summary": "Connecting to leader order stream",
      "detail": {
        "userId": "FEK088"
      }
    },
    {
      "at": "2026-04-13T04:00:05.463Z",
      "type": "mirror.dry_run",
      "summary": "Dry-run follower order prepared",
      "detail": {
        "orderId": "260413150295943",
        "followerId": "follower_2",
        "followerOrder": {
          "variety": "regular",
          "exchange": "NFO",
          "tradingsymbol": "NIFTY2641323650CE",
          "transaction_type": "BUY",
          "order_type": "LIMIT",
          "quantity": 65,
          "product": "NRML",
          "validity": "DAY",
          "disclosed_quantity": 0,
          "price": 54.6,
          "trigger_price": 0,
          "tag": "CPY50295943"
        }
      }
    },
    {
      "at": "2026-04-13T04:00:05.462Z",
      "type": "mirror.dry_run",
      "summary": "Dry-run follower order prepared",
      "detail": {
        "orderId": "260413150295943",
        "followerId": "follower_1",
        "followerOrder": {
          "variety": "regular",
          "exchange": "NFO",
          "tradingsymbol": "NIFTY2641323650CE",
          "transaction_type": "BUY",
          "order_type": "LIMIT",
          "quantity": 65,
          "product": "NRML",
          "validity": "DAY",
          "disclosed_quantity": 0,
          "price": 54.6,
          "trigger_price": 0,
          "tag": "CPY50295943"
        }
      }
    },
    {
      "at": "2026-04-13T04:00:05.460Z",
      "type": "mirror.waiting",
      "summary": "Source order not actionable yet",
      "detail": {
        "orderId": "260413150295943",
        "status": "OPEN"
      }
    },
    {
      "at": "2026-04-13T03:59:08.071Z",
      "type": "mirror.dry_run",
      "summary": "Dry-run follower order prepared",
      "detail": {
        "orderId": "260413150286981",
        "followerId": "follower_2",
        "followerOrder": {
          "variety": "regular",
          "exchange": "NFO",
          "tradingsymbol": "NIFTY2641323650CE",
          "transaction_type": "SELL",
          "order_type": "LIMIT",
          "quantity": 65,
          "product": "NRML",
          "validity": "DAY",
          "disclosed_quantity": 0,
          "price": 52.35,
          "trigger_price": 0,
          "tag": "CPY50286981"
        }
      }
    },
    {
      "at": "2026-04-13T03:59:08.069Z",
      "type": "mirror.dry_run",
      "summary": "Dry-run follower order prepared",
      "detail": {
        "orderId": "260413150286981",
        "followerId": "follower_1",
        "followerOrder": {
          "variety": "regular",
          "exchange": "NFO",
          "tradingsymbol": "NIFTY2641323650CE",
          "transaction_type": "SELL",
          "order_type": "LIMIT",
          "quantity": 65,
          "product": "NRML",
          "validity": "DAY",
          "disclosed_quantity": 0,
          "price": 52.35,
          "trigger_price": 0,
          "tag": "CPY50286981"
        }
      }
    },
    {
      "at": "2026-04-13T03:59:08.067Z",
      "type": "mirror.waiting",
      "summary": "Source order not actionable yet",
      "detail": {
        "orderId": "260413150286981",
        "status": "OPEN"
      }
    },
    {
      "at": "2026-04-13T03:56:00.810Z",
      "type": "stream.connected",
      "summary": "Leader order stream connected",
      "detail": {
        "userId": "FEK088"
      }
    },
    {
      "at": "2026-04-13T03:56:00.760Z",
      "type": "stream.connecting",
      "summary": "Connecting to leader order stream",
      "detail": {
        "userId": "FEK088"
      }
    },
    {
      "at": "2026-04-13T03:56:00.759Z",
      "type": "auth.success",
      "summary": "leader account authenticated",
      "detail": {
        "account": "leader",
        "userId": "FEK088"
      }
    },
    {
      "at": "2026-04-13T03:54:45.602Z",
      "type": "stream.connected",
      "summary": "Leader order stream connected",
      "detail": {
        "userId": "FEK088"
      }
    },
    {
      "at": "2026-04-13T03:54:45.269Z",
      "type": "stream.connecting",
      "summary": "Connecting to leader order stream",
      "detail": {
        "userId": "FEK088"
      }
    },
    {
      "at": "2026-04-13T03:45:23.603Z",
      "type": "stream.skip",
      "summary": "Leader token expired – re-authenticate before market opens"
    },
    {
      "at": "2026-04-13T03:45:23.602Z",
      "type": "auth.expired",
      "summary": "follower_1 token expired (16h 23m). Re-authenticate.",
      "detail": {
        "account": "follower_1"
      }
    },
    {
      "at": "2026-04-13T03:45:23.601Z",
      "type": "auth.expired",
      "summary": "leader token expired (72h 16m). Re-authenticate.",
      "detail": {
        "account": "leader"
      }
    },
    {
      "at": "2026-04-12T11:20:05.565Z",
      "type": "stream.skip",
      "summary": "Leader token expired – re-authenticate before market opens"
    },
    {
      "at": "2026-04-12T11:20:05.564Z",
      "type": "auth.expired",
      "summary": "follower_1 token expired (55h 47m). Re-authenticate.",
      "detail": {
        "account": "follower_1"
      }
    },
    {
      "at": "2026-04-12T11:20:05.562Z",
      "type": "auth.expired",
      "summary": "leader token expired (55h 51m). Re-authenticate.",
      "detail": {
        "account": "leader"
      }
    },
    {
      "at": "2026-04-10T09:39:56.532Z",
      "type": "mirror.error",
      "summary": "Failed to process source order",
      "detail": {
        "orderId": "260410151415533",
        "message": "`quantity` should be multiple of 65."
      }
    },
    {
      "at": "2026-04-10T09:39:56.460Z",
      "type": "mirror.waiting",
      "summary": "Source order update not actionable yet",
      "detail": {
        "orderId": "260410151415533",
        "status": "OPEN"
      }
    },
    {
      "at": "2026-04-10T09:34:42.300Z",
      "type": "mirror.error",
      "summary": "Failed to process source order",
      "detail": {
        "orderId": "260410151389173",
        "message": "`quantity` should be multiple of 65."
      }
    },
    {
      "at": "2026-04-10T09:34:42.229Z",
      "type": "mirror.waiting",
      "summary": "Source order update not actionable yet",
      "detail": {
        "orderId": "260410151389173",
        "status": "OPEN"
      }
    },
    {
      "at": "2026-04-10T09:17:12.286Z",
      "type": "mirror.placed",
      "summary": "Follower order placed",
      "detail": {
        "sourceOrderId": "260410151324783",
        "followerOrderId": "260410171245500",
        "attempt": 1,
        "followerOrder": {
          "variety": "regular",
          "exchange": "NFO",
          "tradingsymbol": "NIFTY2641324200CE",
          "transaction_type": "BUY",
          "order_type": "LIMIT",
          "quantity": 65,
          "product": "NRML",
          "validity": "DAY",
          "disclosed_quantity": 0,
          "price": 54.45,
          "trigger_price": 0,
          "tag": "CPY51324783"
        }
      }
    },
    {
      "at": "2026-04-10T09:17:12.217Z",
      "type": "mirror.waiting",
      "summary": "Source order update not actionable yet",
      "detail": {
        "orderId": "260410151324783",
        "status": "UPDATE"
      }
    },
    {
      "at": "2026-04-10T09:17:12.217Z",
      "type": "mirror.waiting",
      "summary": "Source order update not actionable yet",
      "detail": {
        "orderId": "260410151324783",
        "status": "OPEN"
      }
    },
    {
      "at": "2026-04-10T09:04:20.324Z",
      "type": "mirror.placed",
      "summary": "Follower order placed",
      "detail": {
        "sourceOrderId": "260410151284078",
        "followerOrderId": "260410171204787",
        "attempt": 1,
        "followerOrder": {
          "variety": "regular",
          "exchange": "NFO",
          "tradingsymbol": "NIFTY2641324200CE",
          "transaction_type": "SELL",
          "order_type": "LIMIT",
          "quantity": 65,
          "product": "NRML",
          "validity": "DAY",
          "disclosed_quantity": 0,
          "price": 56.5,
          "trigger_price": 0,
          "market_protection": "0",
          "tag": "CPY51284078"
        }
      }
    },
    {
      "at": "2026-04-10T08:38:24.884Z",
      "type": "mirror.placed",
      "summary": "Follower order placed",
      "detail": {
        "sourceOrderId": "260410151175151",
        "followerOrderId": "260410171096738",
        "attempt": 1,
        "followerOrder": {
          "variety": "regular",
          "exchange": "NFO",
          "tradingsymbol": "NIFTY2641324200CE",
          "transaction_type": "BUY",
          "order_type": "LIMIT",
          "quantity": 65,
          "product": "NRML",
          "validity": "DAY",
          "disclosed_quantity": 0,
          "price": 71.65,
          "trigger_price": 0,
          "tag": "CPY51175151"
        }
      }
    },
    {
      "at": "2026-04-10T08:38:24.825Z",
      "type": "mirror.waiting",
      "summary": "Source order update not actionable yet",
      "detail": {
        "orderId": "260410151175151",
        "status": "UPDATE"
      }
    },
    {
      "at": "2026-04-10T08:38:24.824Z",
      "type": "mirror.waiting",
      "summary": "Source order update not actionable yet",
      "detail": {
        "orderId": "260410151175151",
        "status": "UPDATE"
      }
    },
    {
      "at": "2026-04-10T08:38:24.823Z",
      "type": "mirror.waiting",
      "summary": "Source order update not actionable yet",
      "detail": {
        "orderId": "260410151175151",
        "status": "OPEN"
      }
    },
    {
      "at": "2026-04-10T08:35:06.035Z",
      "type": "mirror.placed",
      "summary": "Follower order placed",
      "detail": {
        "sourceOrderId": "260410151167003",
        "followerOrderId": "260410171089029",
        "attempt": 1,
        "followerOrder": {
          "variety": "regular",
          "exchange": "NFO",
          "tradingsymbol": "NIFTY2641324200CE",
          "transaction_type": "SELL",
          "order_type": "LIMIT",
          "quantity": 65,
          "product": "NRML",
          "validity": "DAY",
          "disclosed_quantity": 0,
          "price": 75.7,
          "trigger_price": 0,
          "tag": "CPY51167003"
        }
      }
    },
    {
      "at": "2026-04-10T08:35:05.959Z",
      "type": "mirror.waiting",
      "summary": "Source order update not actionable yet",
      "detail": {
        "orderId": "260410151167003",
        "status": "UPDATE"
      }
    },
    {
      "at": "2026-04-10T08:35:05.959Z",
      "type": "mirror.waiting",
      "summary": "Source order update not actionable yet",
      "detail": {
        "orderId": "260410151167003",
        "status": "UPDATE"
      }
    },
    {
      "at": "2026-04-10T08:35:05.958Z",
      "type": "mirror.waiting",
      "summary": "Source order update not actionable yet",
      "detail": {
        "orderId": "260410151167003",
        "status": "UPDATE"
      }
    },
    {
      "at": "2026-04-10T08:35:05.957Z",
      "type": "mirror.waiting",
      "summary": "Source order update not actionable yet",
      "detail": {
        "orderId": "260410151167003",
        "status": "UPDATE"
      }
    },
    {
      "at": "2026-04-10T08:35:05.957Z",
      "type": "mirror.waiting",
      "summary": "Source order update not actionable yet",
      "detail": {
        "orderId": "260410151167003",
        "status": "OPEN"
      }
    },
    {
      "at": "2026-04-10T05:31:27.565Z",
      "type": "mirror.placed",
      "summary": "Follower order placed",
      "detail": {
        "sourceOrderId": "260410150700173",
        "followerOrderId": "260410170637166",
        "attempt": 1,
        "followerOrder": {
          "variety": "regular",
          "exchange": "NFO",
          "tradingsymbol": "NIFTY2641323700PE",
          "transaction_type": "BUY",
          "order_type": "LIMIT",
          "quantity": 65,
          "product": "NRML",
          "validity": "DAY",
          "disclosed_quantity": 0,
          "price": 51.05,
          "trigger_price": 0,
          "tag": "CPY50700173"
        }
      }
    },
    {
      "at": "2026-04-10T05:31:27.491Z",
      "type": "mirror.waiting",
      "summary": "Source order update not actionable yet",
      "detail": {
        "orderId": "260410150700173",
        "status": "UPDATE"
      }
    },
    {
      "at": "2026-04-10T05:31:27.491Z",
      "type": "mirror.waiting",
      "summary": "Source order update not actionable yet",
      "detail": {
        "orderId": "260410150700173",
        "status": "UPDATE"
      }
    },
    {
      "at": "2026-04-10T05:31:27.490Z",
      "type": "mirror.waiting",
      "summary": "Source order update not actionable yet",
      "detail": {
        "orderId": "260410150700173",
        "status": "UPDATE"
      }
    },
    {
      "at": "2026-04-10T05:31:27.489Z",
      "type": "mirror.waiting",
      "summary": "Source order update not actionable yet",
      "detail": {
        "orderId": "260410150700173",
        "status": "OPEN"
      }
    },
    {
      "at": "2026-04-10T05:30:55.002Z",
      "type": "mirror.placed",
      "summary": "Follower order placed",
      "detail": {
        "sourceOrderId": "260410150697769",
        "followerOrderId": "260410170634914",
        "attempt": 1,
        "followerOrder": {
          "variety": "regular",
          "exchange": "NFO",
          "tradingsymbol": "NIFTY2641323700PE",
          "transaction_type": "SELL",
          "order_type": "LIMIT",
          "quantity": 65,
          "product": "NRML",
          "validity": "DAY",
          "disclosed_quantity": 0,
          "price": 53.6,
          "trigger_price": 0,
          "tag": "CPY50697769"
        }
      }
    },
    {
      "at": "2026-04-10T05:30:54.936Z",
      "type": "mirror.waiting",
      "summary": "Source order update not actionable yet",
      "detail": {
        "orderId": "260410150697769",
        "status": "UPDATE"
      }
    },
    {
      "at": "2026-04-10T05:30:54.935Z",
      "type": "mirror.waiting",
      "summary": "Source order update not actionable yet",
      "detail": {
        "orderId": "260410150697769",
        "status": "UPDATE"
      }
    },
    {
      "at": "2026-04-10T05:30:54.934Z",
      "type": "mirror.waiting",
      "summary": "Source order update not actionable yet",
      "detail": {
        "orderId": "260410150697769",
        "status": "UPDATE"
      }
    },
    {
      "at": "2026-04-10T05:30:54.933Z",
      "type": "mirror.waiting",
      "summary": "Source order update not actionable yet",
      "detail": {
        "orderId": "260410150697769",
        "status": "OPEN"
      }
    },
    {
      "at": "2026-04-10T05:11:42.103Z",
      "type": "mirror.placed",
      "summary": "Follower order placed",
      "detail": {
        "sourceOrderId": "260410150632738",
        "followerOrderId": "260410170572867",
        "attempt": 1,
        "followerOrder": {
          "variety": "regular",
          "exchange": "NFO",
          "tradingsymbol": "NIFTY2641324200CE",
          "transaction_type": "BUY",
          "order_type": "LIMIT",
          "quantity": 65,
          "product": "NRML",
          "validity": "DAY",
          "disclosed_quantity": 0,
          "price": 72.6,
          "trigger_price": 0,
          "tag": "CPY50632738"
        }
      }
    },
    {
      "at": "2026-04-10T05:11:42.008Z",
      "type": "mirror.waiting",
      "summary": "Source order update not actionable yet",
      "detail": {
        "orderId": "260410150632738",
        "status": "UPDATE"
      }
    },
    {
      "at": "2026-04-10T05:11:42.007Z",
      "type": "mirror.waiting",
      "summary": "Source order update not actionable yet",
      "detail": {
        "orderId": "260410150632738",
        "status": "UPDATE"
      }
    },
    {
      "at": "2026-04-10T05:11:42.006Z",
      "type": "mirror.waiting",
      "summary": "Source order update not actionable yet",
      "detail": {
        "orderId": "260410150632738",
        "status": "UPDATE"
      }
    },
    {
      "at": "2026-04-10T05:11:42.005Z",
      "type": "mirror.waiting",
      "summary": "Source order update not actionable yet",
      "detail": {
        "orderId": "260410150632738",
        "status": "OPEN"
      }
    },
    {
      "at": "2026-04-10T05:00:17.675Z",
      "type": "mirror.placed",
      "summary": "Follower order placed",
      "detail": {
        "sourceOrderId": "260410150593362",
        "followerOrderId": "260410170536113",
        "attempt": 1,
        "followerOrder": {
          "variety": "regular",
          "exchange": "NFO",
          "tradingsymbol": "NIFTY2641324200CE",
          "transaction_type": "SELL",
          "order_type": "LIMIT",
          "quantity": 65,
          "product": "NRML",
          "validity": "DAY",
          "disclosed_quantity": 0,
          "price": 74.5,
          "trigger_price": 0,
          "tag": "CPY50593362"
        }
      }
    },
    {
      "at": "2026-04-10T05:00:17.577Z",
      "type": "mirror.waiting",
      "summary": "Source order update not actionable yet",
      "detail": {
        "orderId": "260410150593362",
        "status": "UPDATE"
      }
    },
    {
      "at": "2026-04-10T05:00:17.576Z",
      "type": "mirror.waiting",
      "summary": "Source order update not actionable yet",
      "detail": {
        "orderId": "260410150593362",
        "status": "UPDATE"
      }
    },
    {
      "at": "2026-04-10T05:00:17.575Z",
      "type": "mirror.waiting",
      "summary": "Source order update not actionable yet",
      "detail": {
        "orderId": "260410150593362",
        "status": "UPDATE"
      }
    },
    {
      "at": "2026-04-10T05:00:17.574Z",
      "type": "mirror.waiting",
      "summary": "Source order update not actionable yet",
      "detail": {
        "orderId": "260410150593362",
        "status": "OPEN"
      }
    },
    {
      "at": "2026-04-10T03:52:04.887Z",
      "type": "mirror.error",
      "summary": "Failed to process source order",
      "detail": {
        "orderId": "260410150156466",
        "message": "`quantity` should be multiple of 65."
      }
    },
    {
      "at": "2026-04-10T03:52:04.833Z",
      "type": "mirror.ignored",
      "summary": "Skipped duplicate source order while processing is already in progress",
      "detail": {
        "orderId": "260410150156466",
        "status": "UPDATE"
      }
    },
    {
      "at": "2026-04-10T03:52:04.832Z",
      "type": "mirror.ignored",
      "summary": "Skipped duplicate source order while processing is already in progress",
      "detail": {
        "orderId": "260410150156466",
        "status": "UPDATE"
      }
    },
    {
      "at": "2026-04-10T03:52:04.830Z",
      "type": "mirror.waiting",
      "summary": "Source order update not actionable yet",
      "detail": {
        "orderId": "260410150156466",
        "status": "UPDATE"
      }
    },
    {
      "at": "2026-04-10T03:52:04.829Z",
      "type": "mirror.waiting",
      "summary": "Source order update not actionable yet",
      "detail": {
        "orderId": "260410150156466",
        "status": "OPEN"
      }
    },
    {
      "at": "2026-04-10T03:51:42.177Z",
      "type": "mirror.error",
      "summary": "Failed to process source order",
      "detail": {
        "orderId": "260410150152472",
        "message": "`quantity` should be multiple of 65."
      }
    },
    {
      "at": "2026-04-10T03:51:42.121Z",
      "type": "mirror.waiting",
      "summary": "Source order update not actionable yet",
      "detail": {
        "orderId": "260410150152472",
        "status": "OPEN"
      }
    },
    {
      "at": "2026-04-10T03:48:50.424Z",
      "type": "mirror.placed",
      "summary": "Follower order placed",
      "detail": {
        "sourceOrderId": "260410150114444",
        "followerOrderId": "260410170098097",
        "attempt": 1,
        "followerOrder": {
          "variety": "regular",
          "exchange": "NFO",
          "tradingsymbol": "NIFTY2641324150CE",
          "transaction_type": "BUY",
          "order_type": "LIMIT",
          "quantity": 65,
          "product": "NRML",
          "validity": "DAY",
          "disclosed_quantity": 0,
          "price": 72.8,
          "trigger_price": 0,
          "tag": "CPY50114444"
        }
      }
    },
    {
      "at": "2026-04-10T03:48:50.355Z",
      "type": "mirror.waiting",
      "summary": "Source order update not actionable yet",
      "detail": {
        "orderId": "260410150114444",
        "status": "UPDATE"
      }
    },
    {
      "at": "2026-04-10T03:48:50.355Z",
      "type": "mirror.waiting",
      "summary": "Source order update not actionable yet",
      "detail": {
        "orderId": "260410150114444",
        "status": "UPDATE"
      }
    },
    {
      "at": "2026-04-10T03:48:50.354Z",
      "type": "mirror.waiting",
      "summary": "Source order update not actionable yet",
      "detail": {
        "orderId": "260410150114444",
        "status": "UPDATE"
      }
    },
    {
      "at": "2026-04-10T03:48:50.353Z",
      "type": "mirror.waiting",
      "summary": "Source order update not actionable yet",
      "detail": {
        "orderId": "260410150114444",
        "status": "UPDATE"
      }
    },
    {
      "at": "2026-04-10T03:48:50.352Z",
      "type": "mirror.waiting",
      "summary": "Source order update not actionable yet",
      "detail": {
        "orderId": "260410150114444",
        "status": "UPDATE"
      }
    },
    {
      "at": "2026-04-10T03:48:50.351Z",
      "type": "mirror.waiting",
      "summary": "Source order update not actionable yet",
      "detail": {
        "orderId": "260410150114444",
        "status": "OPEN"
      }
    },
    {
      "at": "2026-04-10T03:48:42.534Z",
      "type": "mirror.placed",
      "summary": "Follower order placed",
      "detail": {
        "sourceOrderId": "260410150112559",
        "followerOrderId": "260410170096414",
        "attempt": 1,
        "followerOrder": {
          "variety": "regular",
          "exchange": "NFO",
          "tradingsymbol": "NIFTY2641324150CE",
          "transaction_type": "SELL",
          "order_type": "LIMIT",
          "quantity": 65,
          "product": "NRML",
          "validity": "DAY",
          "disclosed_quantity": 0,
          "price": 73.7,
          "trigger_price": 0,
          "tag": "CPY50112559"
        }
      }
    },
    {
      "at": "2026-04-10T03:48:42.452Z",
      "type": "mirror.waiting",
      "summary": "Source order update not actionable yet",
      "detail": {
        "orderId": "260410150112559",
        "status": "UPDATE"
      }
    },
    {
      "at": "2026-04-10T03:48:42.451Z",
      "type": "mirror.waiting",
      "summary": "Source order update not actionable yet",
      "detail": {
        "orderId": "260410150112559",
        "status": "UPDATE"
      }
    },
    {
      "at": "2026-04-10T03:48:42.450Z",
      "type": "mirror.waiting",
      "summary": "Source order update not actionable yet",
      "detail": {
        "orderId": "260410150112559",
        "status": "OPEN"
      }
    },
    {
      "at": "2026-04-10T03:47:36.483Z",
      "type": "stream.connected",
      "summary": "Leader order stream connected",
      "detail": {
        "userId": "FEK088"
      }
    },
    {
      "at": "2026-04-10T03:47:36.379Z",
      "type": "stream.connecting",
      "summary": "Connecting to leader order stream",
      "detail": {
        "userId": "FEK088"
      }
    },
    {
      "at": "2026-04-10T03:32:44.757Z",
      "type": "auth.success",
      "summary": "follower account authenticated",
      "detail": {
        "account": "follower",
        "userId": "QKR315",
        "loginTime": "2026-04-10 09:02:44"
      }
    },
    {
      "at": "2026-04-10T03:28:24.161Z",
      "type": "stream.connected",
      "summary": "Leader order stream connected",
      "detail": {
        "userId": "FEK088"
      }
    },
    {
      "at": "2026-04-10T03:28:24.093Z",
      "type": "stream.connecting",
      "summary": "Connecting to leader order stream",
      "detail": {
        "userId": "FEK088"
      }
    },
    {
      "at": "2026-04-10T03:28:24.092Z",
      "type": "auth.success",
      "summary": "leader account authenticated",
      "detail": {
        "account": "leader",
        "userId": "FEK088",
        "loginTime": "2026-04-10 08:55:35"
      }
    },
    {
      "at": "2026-04-07T05:02:45.233Z",
      "type": "auth.success",
      "summary": "follower account authenticated",
      "detail": {
        "account": "follower",
        "userId": "QKR315",
        "loginTime": "2026-04-07 10:32:45"
      }
    },
    {
      "at": "2026-04-07T01:36:19.798Z",
      "type": "stream.token_expired",
      "summary": "Leader token expired (age: 16h 2m). Re-authenticate to resume.",
      "detail": {
        "userId": "FEK088",
        "tokenAge": "16h 2m"
      }
    },
    {
      "at": "2026-04-07T01:36:17.796Z",
      "type": "stream.reconnect_scheduled",
      "summary": "Reconnecting in 2s (attempt 1)"
    },
    {
      "at": "2026-04-07T01:36:17.795Z",
      "type": "stream.closed",
      "summary": "Leader order stream closed",
      "detail": {
        "code": 1006,
        "reason": "No reason provided"
      }
    },
    {
      "at": "2026-04-06T09:42:36.186Z",
      "type": "cancel.live",
      "summary": "Follower order cancellation sent",
      "detail": {
        "sourceOrderId": "260406151584403",
        "followerOrderId": "260406171535213"
      }
    },
    {
      "at": "2026-04-06T09:42:36.184Z",
      "type": "cancel.live",
      "summary": "Follower order cancellation sent",
      "detail": {
        "sourceOrderId": "260406151584403",
        "followerOrderId": "260406171535213"
      }
    },
    {
      "at": "2026-04-06T09:42:11.200Z",
      "type": "mirror.placed",
      "summary": "Follower order placed",
      "detail": {
        "sourceOrderId": "260406151584403",
        "followerOrderId": "260406171535213",
        "attempt": 1,
        "followerOrder": {
          "variety": "regular",
          "exchange": "NFO",
          "tradingsymbol": "NIFTY2640723200CE",
          "transaction_type": "BUY",
          "order_type": "LIMIT",
          "quantity": 65,
          "product": "NRML",
          "validity": "DAY",
          "disclosed_quantity": 0,
          "price": 80,
          "trigger_price": 0,
          "market_protection": "0",
          "tag": "CPY51584403"
        }
      }
    },
    {
      "at": "2026-04-06T09:38:31.843Z",
      "type": "mirror.placed",
      "summary": "Follower order placed",
      "detail": {
        "sourceOrderId": "260406151570234",
        "followerOrderId": "260406171521022",
        "attempt": 1,
        "followerOrder": {
          "variety": "regular",
          "exchange": "NFO",
          "tradingsymbol": "NIFTY2640723500CE",
          "transaction_type": "BUY",
          "order_type": "LIMIT",
          "quantity": 65,
          "product": "NRML",
          "validity": "DAY",
          "disclosed_quantity": 0,
          "price": 26.25,
          "trigger_price": 0,
          "tag": "CPY51570234"
        }
      }
    },
    {
      "at": "2026-04-06T09:38:31.756Z",
      "type": "mirror.waiting",
      "summary": "Source order update not actionable yet",
      "detail": {
        "orderId": "260406151570234",
        "status": "OPEN"
      }
    },
    {
      "at": "2026-04-06T09:38:05.443Z",
      "type": "mirror.placed",
      "summary": "Follower order placed",
      "detail": {
        "sourceOrderId": "260406151568752",
        "followerOrderId": "260406171519468",
        "attempt": 1,
        "followerOrder": {
          "variety": "regular",
          "exchange": "NFO",
          "tradingsymbol": "NIFTY2640723500CE",
          "transaction_type": "SELL",
          "order_type": "LIMIT",
          "quantity": 65,
          "product": "NRML",
          "validity": "DAY",
          "disclosed_quantity": 0,
          "price": 26.35,
          "trigger_price": 0,
          "tag": "CPY51568752"
        }
      }
    },
    {
      "at": "2026-04-06T09:38:05.369Z",
      "type": "mirror.waiting",
      "summary": "Source order update not actionable yet",
      "detail": {
        "orderId": "260406151568752",
        "status": "OPEN"
      }
    },
    {
      "at": "2026-04-06T09:35:58.837Z",
      "type": "mirror.placed",
      "summary": "Follower order placed",
      "detail": {
        "sourceOrderId": "260406151560204",
        "followerOrderId": "260406171511029",
        "attempt": 1,
        "followerOrder": {
          "variety": "regular",
          "exchange": "NFO",
          "tradingsymbol": "NIFTY2640723200CE",
          "transaction_type": "SELL",
          "order_type": "LIMIT",
          "quantity": 65,
          "product": "NRML",
          "validity": "DAY",
          "disclosed_quantity": 0,
          "price": 90.1,
          "trigger_price": 0,
          "tag": "CPY51560204"
        }
      }
    },
    {
      "at": "2026-04-06T09:35:58.759Z",
      "type": "mirror.waiting",
      "summary": "Source order update not actionable yet",
      "detail": {
        "orderId": "260406151560204",
        "status": "OPEN"
      }
    },
    {
      "at": "2026-04-06T09:35:46.988Z",
      "type": "mirror.placed",
      "summary": "Follower order placed",
      "detail": {
        "sourceOrderId": "260406151559342",
        "followerOrderId": "260406171510174",
        "attempt": 1,
        "followerOrder": {
          "variety": "regular",
          "exchange": "NFO",
          "tradingsymbol": "NIFTY2640723200CE",
          "transaction_type": "BUY",
          "order_type": "LIMIT",
          "quantity": 65,
          "product": "NRML",
          "validity": "DAY",
          "disclosed_quantity": 0,
          "price": 88.95,
          "trigger_price": 0,
          "tag": "CPY51559342"
        }
      }
    },
    {
      "at": "2026-04-06T09:35:46.925Z",
      "type": "mirror.waiting",
      "summary": "Source order update not actionable yet",
      "detail": {
        "orderId": "260406151559342",
        "status": "OPEN"
      }
    },
    {
      "at": "2026-04-06T09:33:30.973Z",
      "type": "auth.success",
      "summary": "follower account authenticated",
      "detail": {
        "account": "follower",
        "userId": "QKR315",
        "loginTime": "2026-04-06 15:03:30"
      }
    },
    {
      "at": "2026-04-06T09:33:23.768Z",
      "type": "stream.connected",
      "summary": "Leader order stream connected",
      "detail": {
        "userId": "FEK088"
      }
    },
    {
      "at": "2026-04-06T09:33:23.714Z",
      "type": "stream.connecting",
      "summary": "Connecting to leader order stream",
      "detail": {
        "userId": "FEK088"
      }
    },
    {
      "at": "2026-04-06T09:33:23.714Z",
      "type": "auth.success",
      "summary": "leader account authenticated",
      "detail": {
        "account": "leader",
        "userId": "FEK088",
        "loginTime": "2026-04-06 09:06:36"
      }
    },
    {
      "at": "2026-04-05T17:50:15.138Z",
      "type": "stream.skip",
      "summary": "Leader token is expired – re-authenticate the leader account before market opens"
    },
    {
      "at": "2026-04-05T17:50:15.137Z",
      "type": "auth.expired",
      "summary": "follower token appears expired (age: 84h 51m). Please re-authenticate.",
      "detail": {
        "account": "follower",
        "userId": "QKR315",
        "tokenAge": "84h 51m"
      }
    },
    {
      "at": "2026-04-05T17:50:15.136Z",
      "type": "auth.expired",
      "summary": "leader token appears expired (age: 84h 49m). Please re-authenticate.",
      "detail": {
        "account": "leader",
        "userId": "FEK088",
        "tokenAge": "84h 49m"
      }
    },
    {
      "at": "2026-04-02T05:04:40.830Z",
      "type": "stream.connected",
      "summary": "Leader order stream connected",
      "detail": {
        "userId": "FEK088"
      }
    },
    {
      "at": "2026-04-02T05:04:40.811Z",
      "type": "stream.reconnect_scheduled",
      "summary": "Reconnecting in 2s (attempt 1)"
    },
    {
      "at": "2026-04-02T05:04:40.811Z",
      "type": "stream.closed",
      "summary": "Leader order stream closed",
      "detail": {
        "code": 1005,
        "reason": "No reason provided"
      }
    },
    {
      "at": "2026-04-02T05:04:40.806Z",
      "type": "stream.connecting",
      "summary": "Connecting to leader order stream",
      "detail": {
        "userId": "FEK088"
      }
    },
    {
      "at": "2026-04-02T05:04:38.830Z",
      "type": "stream.connected",
      "summary": "Leader order stream connected",
      "detail": {
        "userId": "FEK088"
      }
    },
    {
      "at": "2026-04-02T05:04:38.804Z",
      "type": "stream.reconnect_scheduled",
      "summary": "Reconnecting in 2s (attempt 1)"
    },
    {
      "at": "2026-04-02T05:04:38.804Z",
      "type": "stream.closed",
      "summary": "Leader order stream closed",
      "detail": {
        "code": 1005,
        "reason": "No reason provided"
      }
    },
    {
      "at": "2026-04-02T05:04:38.800Z",
      "type": "stream.connecting",
      "summary": "Connecting to leader order stream",
      "detail": {
        "userId": "FEK088"
      }
    },
    {
      "at": "2026-04-02T05:04:36.814Z",
      "type": "stream.connected",
      "summary": "Leader order stream connected",
      "detail": {
        "userId": "FEK088"
      }
    },
    {
      "at": "2026-04-02T05:04:36.797Z",
      "type": "stream.reconnect_scheduled",
      "summary": "Reconnecting in 2s (attempt 1)"
    },
    {
      "at": "2026-04-02T05:04:36.797Z",
      "type": "stream.closed",
      "summary": "Leader order stream closed",
      "detail": {
        "code": 1005,
        "reason": "No reason provided"
      }
    },
    {
      "at": "2026-04-02T05:04:36.792Z",
      "type": "stream.connecting",
      "summary": "Connecting to leader order stream",
      "detail": {
        "userId": "FEK088"
      }
    },
    {
      "at": "2026-04-02T05:04:34.808Z",
      "type": "stream.connected",
      "summary": "Leader order stream connected",
      "detail": {
        "userId": "FEK088"
      }
    },
    {
      "at": "2026-04-02T05:04:34.792Z",
      "type": "stream.reconnect_scheduled",
      "summary": "Reconnecting in 2s (attempt 1)"
    },
    {
      "at": "2026-04-02T05:04:34.791Z",
      "type": "stream.closed",
      "summary": "Leader order stream closed",
      "detail": {
        "code": 1005,
        "reason": "No reason provided"
      }
    },
    {
      "at": "2026-04-02T05:04:34.786Z",
      "type": "stream.connecting",
      "summary": "Connecting to leader order stream",
      "detail": {
        "userId": "FEK088"
      }
    },
    {
      "at": "2026-04-02T05:04:32.805Z",
      "type": "stream.connected",
      "summary": "Leader order stream connected",
      "detail": {
        "userId": "FEK088"
      }
    },
    {
      "at": "2026-04-02T05:04:32.784Z",
      "type": "stream.reconnect_scheduled",
      "summary": "Reconnecting in 2s (attempt 1)"
    },
    {
      "at": "2026-04-02T05:04:32.783Z",
      "type": "stream.closed",
      "summary": "Leader order stream closed",
      "detail": {
        "code": 1005,
        "reason": "No reason provided"
      }
    },
    {
      "at": "2026-04-02T05:04:32.778Z",
      "type": "stream.connecting",
      "summary": "Connecting to leader order stream",
      "detail": {
        "userId": "FEK088"
      }
    },
    {
      "at": "2026-04-02T05:04:30.793Z",
      "type": "stream.connected",
      "summary": "Leader order stream connected",
      "detail": {
        "userId": "FEK088"
      }
    },
    {
      "at": "2026-04-02T05:04:30.776Z",
      "type": "stream.reconnect_scheduled",
      "summary": "Reconnecting in 2s (attempt 1)"
    },
    {
      "at": "2026-04-02T05:04:30.775Z",
      "type": "stream.closed",
      "summary": "Leader order stream closed",
      "detail": {
        "code": 1005,
        "reason": "No reason provided"
      }
    },
    {
      "at": "2026-04-02T05:04:30.771Z",
      "type": "stream.connecting",
      "summary": "Connecting to leader order stream",
      "detail": {
        "userId": "FEK088"
      }
    },
    {
      "at": "2026-04-02T05:04:28.785Z",
      "type": "stream.connected",
      "summary": "Leader order stream connected",
      "detail": {
        "userId": "FEK088"
      }
    },
    {
      "at": "2026-04-02T05:04:28.768Z",
      "type": "stream.reconnect_scheduled",
      "summary": "Reconnecting in 2s (attempt 1)"
    },
    {
      "at": "2026-04-02T05:04:28.767Z",
      "type": "stream.closed",
      "summary": "Leader order stream closed",
      "detail": {
        "code": 1005,
        "reason": "No reason provided"
      }
    },
    {
      "at": "2026-04-02T05:04:28.762Z",
      "type": "stream.connecting",
      "summary": "Connecting to leader order stream",
      "detail": {
        "userId": "FEK088"
      }
    },
    {
      "at": "2026-04-02T05:04:26.782Z",
      "type": "stream.connected",
      "summary": "Leader order stream connected",
      "detail": {
        "userId": "FEK088"
      }
    },
    {
      "at": "2026-04-02T05:04:26.760Z",
      "type": "stream.reconnect_scheduled",
      "summary": "Reconnecting in 2s (attempt 1)"
    },
    {
      "at": "2026-04-02T05:04:26.760Z",
      "type": "stream.closed",
      "summary": "Leader order stream closed",
      "detail": {
        "code": 1005,
        "reason": "No reason provided"
      }
    },
    {
      "at": "2026-04-02T05:04:26.755Z",
      "type": "stream.connecting",
      "summary": "Connecting to leader order stream",
      "detail": {
        "userId": "FEK088"
      }
    },
    {
      "at": "2026-04-02T05:04:24.769Z",
      "type": "stream.connected",
      "summary": "Leader order stream connected",
      "detail": {
        "userId": "FEK088"
      }
    },
    {
      "at": "2026-04-02T05:04:24.753Z",
      "type": "stream.reconnect_scheduled",
      "summary": "Reconnecting in 2s (attempt 1)"
    },
    {
      "at": "2026-04-02T05:04:24.752Z",
      "type": "stream.closed",
      "summary": "Leader order stream closed",
      "detail": {
        "code": 1005,
        "reason": "No reason provided"
      }
    },
    {
      "at": "2026-04-02T05:04:24.748Z",
      "type": "stream.connecting",
      "summary": "Connecting to leader order stream",
      "detail": {
        "userId": "FEK088"
      }
    },
    {
      "at": "2026-04-02T05:04:22.784Z",
      "type": "stream.connected",
      "summary": "Leader order stream connected",
      "detail": {
        "userId": "FEK088"
      }
    },
    {
      "at": "2026-04-02T05:04:22.746Z",
      "type": "stream.reconnect_scheduled",
      "summary": "Reconnecting in 2s (attempt 1)"
    },
    {
      "at": "2026-04-02T05:04:22.746Z",
      "type": "stream.closed",
      "summary": "Leader order stream closed",
      "detail": {
        "code": 1005,
        "reason": "No reason provided"
      }
    },
    {
      "at": "2026-04-02T05:04:22.741Z",
      "type": "stream.connecting",
      "summary": "Connecting to leader order stream",
      "detail": {
        "userId": "FEK088"
      }
    },
    {
      "at": "2026-04-02T05:04:20.754Z",
      "type": "stream.connected",
      "summary": "Leader order stream connected",
      "detail": {
        "userId": "FEK088"
      }
    },
    {
      "at": "2026-04-02T05:04:20.740Z",
      "type": "stream.reconnect_scheduled",
      "summary": "Reconnecting in 2s (attempt 1)"
    },
    {
      "at": "2026-04-02T05:04:20.739Z",
      "type": "stream.closed",
      "summary": "Leader order stream closed",
      "detail": {
        "code": 1005,
        "reason": "No reason provided"
      }
    },
    {
      "at": "2026-04-02T05:04:20.735Z",
      "type": "stream.connecting",
      "summary": "Connecting to leader order stream",
      "detail": {
        "userId": "FEK088"
      }
    },
    {
      "at": "2026-04-02T05:04:18.747Z",
      "type": "stream.connected",
      "summary": "Leader order stream connected",
      "detail": {
        "userId": "FEK088"
      }
    },
    {
      "at": "2026-04-02T05:04:18.732Z",
      "type": "stream.reconnect_scheduled",
      "summary": "Reconnecting in 2s (attempt 1)"
    },
    {
      "at": "2026-04-02T05:04:18.732Z",
      "type": "stream.closed",
      "summary": "Leader order stream closed",
      "detail": {
        "code": 1005,
        "reason": "No reason provided"
      }
    },
    {
      "at": "2026-04-02T05:04:18.727Z",
      "type": "stream.connecting",
      "summary": "Connecting to leader order stream",
      "detail": {
        "userId": "FEK088"
      }
    },
    {
      "at": "2026-04-02T05:04:16.739Z",
      "type": "stream.connected",
      "summary": "Leader order stream connected",
      "detail": {
        "userId": "FEK088"
      }
    },
    {
      "at": "2026-04-02T05:04:16.725Z",
      "type": "stream.reconnect_scheduled",
      "summary": "Reconnecting in 2s (attempt 1)"
    },
    {
      "at": "2026-04-02T05:04:16.725Z",
      "type": "stream.closed",
      "summary": "Leader order stream closed",
      "detail": {
        "code": 1005,
        "reason": "No reason provided"
      }
    },
    {
      "at": "2026-04-02T05:04:16.720Z",
      "type": "stream.connecting",
      "summary": "Connecting to leader order stream",
      "detail": {
        "userId": "FEK088"
      }
    },
    {
      "at": "2026-04-02T05:04:14.741Z",
      "type": "stream.connected",
      "summary": "Leader order stream connected",
      "detail": {
        "userId": "FEK088"
      }
    },
    {
      "at": "2026-04-02T05:04:14.718Z",
      "type": "stream.reconnect_scheduled",
      "summary": "Reconnecting in 2s (attempt 1)"
    },
    {
      "at": "2026-04-02T05:04:14.718Z",
      "type": "stream.closed",
      "summary": "Leader order stream closed",
      "detail": {
        "code": 1005,
        "reason": "No reason provided"
      }
    },
    {
      "at": "2026-04-02T05:04:14.713Z",
      "type": "stream.connecting",
      "summary": "Connecting to leader order stream",
      "detail": {
        "userId": "FEK088"
      }
    },
    {
      "at": "2026-04-02T05:04:12.748Z",
      "type": "stream.connected",
      "summary": "Leader order stream connected",
      "detail": {
        "userId": "FEK088"
      }
    },
    {
      "at": "2026-04-02T05:04:12.711Z",
      "type": "stream.reconnect_scheduled",
      "summary": "Reconnecting in 2s (attempt 1)"
    },
    {
      "at": "2026-04-02T05:04:12.711Z",
      "type": "stream.closed",
      "summary": "Leader order stream closed",
      "detail": {
        "code": 1005,
        "reason": "No reason provided"
      }
    },
    {
      "at": "2026-04-02T05:04:12.706Z",
      "type": "stream.connecting",
      "summary": "Connecting to leader order stream",
      "detail": {
        "userId": "FEK088"
      }
    },
    {
      "at": "2026-04-02T05:04:10.742Z",
      "type": "stream.connected",
      "summary": "Leader order stream connected",
      "detail": {
        "userId": "FEK088"
      }
    },
    {
      "at": "2026-04-02T05:04:10.705Z",
      "type": "stream.reconnect_scheduled",
      "summary": "Reconnecting in 2s (attempt 1)"
    },
    {
      "at": "2026-04-02T05:04:10.704Z",
      "type": "stream.closed",
      "summary": "Leader order stream closed",
      "detail": {
        "code": 1005,
        "reason": "No reason provided"
      }
    }
  ],
  "preConnectPositions": {
    "leader": {},
    "follower_2": {}
  }
}